src/esayege_v1/__init__.py
src/esayege_v1/example.py
example_package_eqehan-0.0.1.dist-info/METADATA
example_package_eqehan-0.0.1.dist-info/WHEEL
example_package_eqehan-0.0.1.dist-info/licenses/LICENSE
example_package_eqehan-0.0.1.dist-info/RECORD
